django_logger/__init__.py
django_logger/admin.py
django_logger/apps.py
django_logger/filters.py
django_logger/handlers.py
django_logger/middleware.py
django_logger/models.py
django_logger/urls.py
django_logger/views.py
django_logger/locale/ en/LC_MESSAGES/django.po
django_logger/locale/ pl/LC_MESSAGES/django.po
django_logger/migrations/0001_initial.py
django_logger/migrations/__init__.py
django_logger/tests/__init__.py
django_logger/tests/models/__init__.py
django_logger/tests/models/test_action.py
django_logger/tests/models/test_event.py
django_logger/tests/models/test_remote.py
dj_logger-0.1.dist-info/LICENSE
dj_logger-0.1.dist-info/METADATA
dj_logger-0.1.dist-info/WHEEL
dj_logger-0.1.dist-info/top_level.txt
dj_logger-0.1.dist-info/RECORD
